trlocal_backup/__init__.py
trlocal_backup/__main__.py
trlocal_backup-0.1.0.dist-info/LICENSE
trlocal_backup-0.1.0.dist-info/WHEEL
trlocal_backup-0.1.0.dist-info/METADATA
trlocal_backup-0.1.0.dist-info/RECORD
