Metadata-Version: 2.1
Name: trlocal-backup
Version: 0.1.0
Summary: a local backup tool for transmission without call remote rpc.
Home-page: https://github.com/Cologler/trlocal_backup-python
License: MIT
Author: Cologler
Author-email: skyoflw@gmail.com
Requires-Python: >=3.8,<4.0
Classifier: License :: OSI Approved :: MIT License
Classifier: Programming Language :: Python :: 3
Classifier: Programming Language :: Python :: 3.8
